LICENSE
MANIFEST.in
README.md
pyproject.toml
setup.py
bin/hamiltonian.py
damealgorithms/runtests.sh
damealgorithms.egg-info/PKG-INFO
damealgorithms.egg-info/SOURCES.txt
damealgorithms.egg-info/dependency_links.txt
damealgorithms.egg-info/entry_points.txt
damealgorithms.egg-info/not-zip-safe
damealgorithms.egg-info/requires.txt
damealgorithms.egg-info/top_level.txt
damealgorithms/src/bfs.py
damealgorithms/src/bst.py
damealgorithms/src/hamiltonian.py
damealgorithms/src/mcolors.py
damealgorithms/src/minmax.py
damealgorithms/src/quicksort.py
damealgorithms/src/shellsort.py
damealgorithms/tests/__init__.py
damealgorithms/tests/test_bfs.py
damealgorithms/tests/test_bst.py
damealgorithms/tests/test_hamiltonian.py
damealgorithms/tests/test_mcolors.py
damealgorithms/tests/test_minmax.py
damealgorithms/tests/test_quicksort.py
damealgorithms/tests/test_shellsort.py